pymatris/__init__.py
pymatris/config.py
pymatris/downloader.py
pymatris/exceptions.py
pymatris/main.py
pymatris/protocol_handler/__init__.py
pymatris/protocol_handler/base_handler.py
pymatris/protocol_handler/ftp_handler.py
pymatris/protocol_handler/http_handler.py
pymatris/protocol_handler/sftp_handler.py
pymatris/results.py
pymatris/utils.py
pymatris/write_worker.py
pymatris-0.0.10.dist-info/METADATA
pymatris-0.0.10.dist-info/WHEEL
pymatris-0.0.10.dist-info/entry_points.txt
pymatris-0.0.10.dist-info/RECORD
